csinsc/__init__.py
csinsc-1.1.0.8.dist-info/LICENSE
csinsc-1.1.0.8.dist-info/METADATA
csinsc-1.1.0.8.dist-info/WHEEL
csinsc-1.1.0.8.dist-info/top_level.txt
csinsc-1.1.0.8.dist-info/RECORD
