Metadata-Version: 2.1
Name: csinsc
Version: 1.1.0.8
Summary: Tools and libraries used in the CSinSchools course
Home-page: https://github.com/toanh/csinsc
Author: Toan Huynh
Author-email: toan@csinschools.io
License: UNKNOWN
Platform: UNKNOWN
Classifier: Programming Language :: Python :: 3
Classifier: License :: OSI Approved :: GNU General Public License v3 (GPLv3)
Classifier: Operating System :: OS Independent
